restocks/__init__.py
restocks/__version__.py
restocks/exceptions.py
restocks/filters.py
restocks/product.py
restocks/client/__init__.py
restocks/client/client.py
restocks/client/core.py
restocks/utils/__init__.py
restocks/utils/helpers.py
restocks/utils/request.py
restocks_client-0.1.3.dist-info/LICENSE
restocks_client-0.1.3.dist-info/METADATA
restocks_client-0.1.3.dist-info/WHEEL
restocks_client-0.1.3.dist-info/top_level.txt
restocks_client-0.1.3.dist-info/RECORD
